odoo8_addon_l10n_lu_fin_rep_details-8.0.0.1.0.99.dev3-py2.7-nspkg.pth
odoo8_addon_l10n_lu_fin_rep_details-8.0.0.1.0.99.dev3.dist-info/METADATA
odoo8_addon_l10n_lu_fin_rep_details-8.0.0.1.0.99.dev3.dist-info/RECORD
odoo8_addon_l10n_lu_fin_rep_details-8.0.0.1.0.99.dev3.dist-info/WHEEL
odoo8_addon_l10n_lu_fin_rep_details-8.0.0.1.0.99.dev3.dist-info/namespace_packages.txt
odoo8_addon_l10n_lu_fin_rep_details-8.0.0.1.0.99.dev3.dist-info/top_level.txt
odoo_addons/l10n_lu_fin_rep_details/__init__.py
odoo_addons/l10n_lu_fin_rep_details/__openerp__.py
odoo_addons/l10n_lu_fin_rep_details/account_financial_report.xml
odoo_addons/l10n_lu_fin_rep_details/account_financial_report_abr.xml
odoo_addons/l10n_lu_fin_rep_details/i18n/l10n_lu_fin_rep_details.pot
odoo_addons/l10n_lu_fin_rep_details/static/description/icon.png
